fugen/__init__.py
fugen/enums.py
fugen/random_module.py
fugen/data/ifns_branches.json
fugen/data/okved_codes.json
fugen/generators/__init__.py
fugen/generators/company.py
fugen/generators/ifns.py
fugen/generators/okved.py
fugen-0.0.1.data/data/ifns_branches.json
fugen-0.0.1.data/data/okved_codes.json
fugen-0.0.1.dist-info/METADATA
fugen-0.0.1.dist-info/WHEEL
fugen-0.0.1.dist-info/top_level.txt
fugen-0.0.1.dist-info/zip-safe
fugen-0.0.1.dist-info/RECORD
